PyECCIntegrity/__init__.py
PyECCIntegrity/integrity.py
pyeccintegrity-0.1.0.dist-info/licenses/LICENSE
pyeccintegrity-0.1.0.dist-info/METADATA
pyeccintegrity-0.1.0.dist-info/WHEEL
pyeccintegrity-0.1.0.dist-info/entry_points.txt
pyeccintegrity-0.1.0.dist-info/top_level.txt
pyeccintegrity-0.1.0.dist-info/RECORD
