Metadata-Version: 2.4
Name: PyECCIntegrity
Version: 0.1.0
Summary: ECC-based Integrity Verification using ECDSA and SHA-256
Home-page: https://github.com/mohdluqman/PyECCIntegrity
Author: Mohammad Luqman, Salman Ali, Faisal Anwer
Author-email: luqman.geeky@gmail.com, salmanali.amu@gmail.com, faisalanwer.cs@amu.ac.in
License: MIT
Classifier: Programming Language :: Python :: 3
Classifier: License :: OSI Approved :: MIT License
Classifier: Operating System :: OS Independent
Requires-Python: >=3.6
License-File: LICENSE
Requires-Dist: cryptography
Dynamic: author
Dynamic: author-email
Dynamic: classifier
Dynamic: description
Dynamic: description-content-type
Dynamic: home-page
Dynamic: license
Dynamic: license-file
Dynamic: requires-dist
Dynamic: requires-python
Dynamic: summary
